tests/__init__.py
tests/test_env.py
tsu/SuBinary.py
tsu/__init__.py
tsu/consts.py
tsu/defs.py
tsu/env_map.py
tsu/exec.py
tsu/main.py
tsu/user_utils.py
tsu-3.5.8.dist-info/LICENSE-MIT
tsu-3.5.8.dist-info/METADATA
tsu-3.5.8.dist-info/WHEEL
tsu-3.5.8.dist-info/entry_points.txt
tsu-3.5.8.dist-info/top_level.txt
tsu-3.5.8.dist-info/RECORD
