Metadata-Version: 2.1
Name: tsu
Version: 3.5.8
Summary: A su wrapper for Termux
Home-page: https://github.com/_/tsu
Author: Cswl coldwind
Author-email: cswl@gmail.com
Maintainer: Cswl coldwind
Maintainer-email: cswl@gmail.com
License: MIT
Platform: UNKNOWN
Classifier: Development Status :: 4 - Beta
Classifier: Intended Audience :: Developers
Classifier: License :: OSI Approved :: MIT License
Classifier: License :: OSI Approved :: Apache Software License
Classifier: Natural Language :: English
Classifier: Operating System :: OS Independent
Classifier: Programming Language :: Python :: 2.7
Classifier: Programming Language :: Python :: 3.5
Classifier: Programming Language :: Python :: 3.6
Classifier: Programming Language :: Python :: Implementation :: CPython
Classifier: Programming Language :: Python :: Implementation :: PyPy
Requires-Dist: docopt
Requires-Dist: wrapt
Requires-Dist: attrs
Requires-Dist: consolejs
